pactus_jsonrpc/__init__.py
pactus_jsonrpc/client.py
pactus_jsonrpc/models.py
pactus_jsonrpc-1.11.1.dist-info/licenses/LICENSE
pactus_jsonrpc-1.11.1.dist-info/METADATA
pactus_jsonrpc-1.11.1.dist-info/WHEEL
pactus_jsonrpc-1.11.1.dist-info/top_level.txt
pactus_jsonrpc-1.11.1.dist-info/RECORD
